prod_cli/__init__.py
prod_cli-2.0.0.dist-info/LICENSE.txt
prod_cli-2.0.0.dist-info/METADATA
prod_cli-2.0.0.dist-info/WHEEL
prod_cli-2.0.0.dist-info/entry_points.txt
prod_cli-2.0.0.dist-info/top_level.txt
prod_cli-2.0.0.dist-info/RECORD
