Metadata-Version: 2.1
Name: prod-cli
Version: 2.0.0
Summary: A prod-cli package
Author-email: Arnaud M <arnaud.pypi@mailops.fr>
Classifier: Programming Language :: Python :: 3
Classifier: License :: OSI Approved :: MIT License
Classifier: Operating System :: OS Independent
Requires-Python: >=3.8
License-File: LICENSE.txt
